clean_panda/__init__.py
clean_panda/cleaner.py
clean_panda/data.py
clean_panda-0.1.3.dist-info/LICENSE
clean_panda-0.1.3.dist-info/METADATA
clean_panda-0.1.3.dist-info/WHEEL
clean_panda-0.1.3.dist-info/top_level.txt
clean_panda-0.1.3.dist-info/RECORD
